panstamps/__init__.py
panstamps/__version__.py
panstamps/cl_utils.py
panstamps/default_settings.yaml
panstamps/downloader.py
panstamps/test_settings.yaml
panstamps/utKit.py
panstamps/commonutils/__init__.py
panstamps/commonutils/getpackagepath.py
panstamps/image/__init__.py
panstamps/image/image.py
panstamps/resources/package.mplstyle
panstamps/resources/ps1.png
panstamps/resources/fonts/source-sans-pro-italic.ttf
panstamps/resources/fonts/source-sans-pro-regular.ttf
panstamps/resources/fonts/source-sans-pro-semibold.ttf
panstamps/resources/fonts/source-sans-pro-semibolditalic.ttf
panstamps-0.6.7.dist-info/LICENSE
panstamps-0.6.7.dist-info/METADATA
panstamps-0.6.7.dist-info/WHEEL
panstamps-0.6.7.dist-info/entry_points.txt
panstamps-0.6.7.dist-info/top_level.txt
panstamps-0.6.7.dist-info/RECORD
