Metadata-Version: 2.1
Name: panstamps
Version: 0.6.7
Summary: Download stacked and/or warp image stamps from the STScI PanSTARRS image server via CL or Python API
Home-page: https://github.com/thespacedoctor/panstamps
Download-URL: https://github.com/thespacedoctor/panstamps/archive/v0.6.7.zip
Author: David Young
Author-email: davidrobertyoung@gmail.com
License: MIT
Keywords: astronomy, images, panstarrs
Classifier: Development Status :: 4 - Beta
Classifier: License :: OSI Approved :: MIT License
Classifier: Programming Language :: Python :: 3.7
Classifier: Topic :: Utilities
License-File: LICENSE
Requires-Dist: pyyaml
Requires-Dist: panstamps
Requires-Dist: fundamentals
Requires-Dist: requests
Requires-Dist: pillow
Requires-Dist: eventlet
Requires-Dist: numpy
Requires-Dist: python-dateutil
